lambdabase/BaseHandler.py
lambdabase/BaseStrap.py
lambdabase/ConfigManager.py
lambdabase/Constants.py
lambdabase/LambdaException.py
lambdabase/Request.py
lambdabase/RequestContext.py
lambdabase/Response.py
lambdabase/Utils.py
lambdabase/__init__.py
lambdabase/data/DynamoDbObjectStore.py
lambdabase/data/MultiMapDatastore.py
lambdabase/data/__init__.py
lambdabase/invokers/Invoker.py
lambdabase/invokers/InvokerFactory.py
lambdabase/invokers/LambdaInvoker.py
lambdabase/invokers/LogFactory.py
lambdabase/invokers/__init__.py
lambdabase/local/CognitoProxy.py
lambdabase/local/JwtValidator.py
lambdabase/local/LambdaProxy.py
lambdabase/local/__init__.py
lambdabase/local/data/MemoryObjectStore.py
lambdabase/local/data/__init__.py
lambdabase/local/invokers/HttpGetInvoker.py
lambdabase/local/invokers/HttpPostInvoker.py
lambdabase/local/invokers/__init__.py
lambdabase/log/LogContextFilter.py
lambdabase/log/LogFactoryBase.py
lambdabase/log/LogMessage.py
lambdabase/log/__init__.py
lambdabase/test/__init__.py
lambdabase/test/unit/__init__.py
lambdabase/test/unit/test_base_handler.py
lambdabase/test/unit/test_multimap_datastore.py
lambdabase-0.7.dist-info/METADATA
lambdabase-0.7.dist-info/RECORD
lambdabase-0.7.dist-info/WHEEL
lambdabase-0.7.dist-info/top_level.txt
