Metadata-Version: 2.1
Name: lambdabase
Version: 0.7
Summary: UNKNOWN
Home-page: https://bitbucket.org/danielbardsley/lambdabase
Author: Daniel Bardsley
Author-email: daniel@bardsley.org.uk
License: UNKNOWN
Platform: UNKNOWN
Classifier: Programming Language :: Python :: 2.7
Classifier: License :: OSI Approved :: MIT License
Classifier: Operating System :: OS Independent
